{
  "last_updated": "2026-07-08 07:03:29 UTC",
  "timeframe": "15m",
  "mtf": "1h",
  "pairs": [
    {
      "symbol": "AUDUSD",
      "price": 0.69391,
      "signal": "WAIT",
      "direction": "BULL",
      "conditions": {
        "trend": true,
        "channel": false,
        "macd": true,
        "mtf": false,
        "ses": false
      },
      "conditions_met": 2
    },
    {
      "symbol": "USDCAD",
      "price": 1.4175,
      "signal": "WAIT",
      "direction": "BEAR",
      "conditions": {
        "trend": false,
        "channel": true,
        "macd": true,
        "mtf": true,
        "ses": false
      },
      "conditions_met": 3
    },
    {
      "symbol": "USDCHF",
      "price": 0.80689,
      "signal": "WAIT",
      "direction": "BULL",
      "conditions": {
        "trend": true,
        "channel": false,
        "macd": false,
        "mtf": true,
        "ses": false
      },
      "conditions_met": 2
    },
    {
      "symbol": "NZDUSD",
      "price": 0.5714,
      "signal": "WAIT",
      "direction": "BULL",
      "conditions": {
        "trend": true,
        "channel": true,
        "macd": true,
        "mtf": true,
        "ses": false
      },
      "conditions_met": 4
    },
    {
      "symbol": "EURJPY",
      "price": 185.27299,
      "signal": "BUY",
      "direction": "BULL",
      "conditions": {
        "trend": true,
        "channel": true,
        "macd": true,
        "mtf": true,
        "ses": true
      },
      "conditions_met": 5
    },
    {
      "symbol": "GBPJPY",
      "price": 216.787,
      "signal": "BUY",
      "direction": "BULL",
      "conditions": {
        "trend": true,
        "channel": true,
        "macd": true,
        "mtf": true,
        "ses": true
      },
      "conditions_met": 5
    },
    {
      "symbol": "EURGBP",
      "price": 0.8546,
      "signal": "WAIT",
      "direction": "BULL",
      "conditions": {
        "trend": true,
        "channel": false,
        "macd": true,
        "mtf": true,
        "ses": false
      },
      "conditions_met": 3
    }
  ]
}