{
  "last_updated": "2026-07-17 08:32:13 UTC",
  "timeframe": "15m",
  "mtf": "1h",
  "pairs": [
    {
      "symbol": "EURUSD",
      "price": 1.1443,
      "signal": "WAIT",
      "direction": "BEAR",
      "conditions": {
        "trend": false,
        "channel": true,
        "macd": false,
        "mtf": true,
        "ses": true
      },
      "conditions_met": 3
    },
    {
      "symbol": "USDJPY",
      "price": 162.408,
      "signal": "WAIT",
      "direction": "BULL",
      "conditions": {
        "trend": true,
        "channel": true,
        "macd": false,
        "mtf": true,
        "ses": true
      },
      "conditions_met": 4
    },
    {
      "symbol": "GBPUSD",
      "price": 1.34506,
      "signal": "WAIT",
      "direction": "BEAR",
      "conditions": {
        "trend": false,
        "channel": true,
        "macd": true,
        "mtf": true,
        "ses": false
      },
      "conditions_met": 3
    },
    {
      "symbol": "AUDUSD",
      "price": 0.69798,
      "signal": "WAIT",
      "direction": "BEAR",
      "conditions": {
        "trend": false,
        "channel": true,
        "macd": true,
        "mtf": true,
        "ses": false
      },
      "conditions_met": 3
    },
    {
      "symbol": "USDCAD",
      "price": 1.40322,
      "signal": "WAIT",
      "direction": "BEAR",
      "conditions": {
        "trend": false,
        "channel": false,
        "macd": true,
        "mtf": true,
        "ses": false
      },
      "conditions_met": 2
    },
    {
      "symbol": "USDCHF",
      "price": 0.80696,
      "signal": "WAIT",
      "direction": "BEAR",
      "conditions": {
        "trend": false,
        "channel": true,
        "macd": true,
        "mtf": false,
        "ses": false
      },
      "conditions_met": 2
    },
    {
      "symbol": "NZDUSD",
      "price": 0.58374,
      "signal": "WAIT",
      "direction": "BEAR",
      "conditions": {
        "trend": false,
        "channel": true,
        "macd": false,
        "mtf": true,
        "ses": true
      },
      "conditions_met": 3
    },
    {
      "symbol": "EURJPY",
      "price": 185.80701,
      "signal": "WAIT",
      "direction": "BEAR",
      "conditions": {
        "trend": false,
        "channel": false,
        "macd": true,
        "mtf": true,
        "ses": false
      },
      "conditions_met": 2
    },
    {
      "symbol": "GBPJPY",
      "price": 218.42101,
      "signal": "WAIT",
      "direction": "BEAR",
      "conditions": {
        "trend": false,
        "channel": true,
        "macd": true,
        "mtf": true,
        "ses": false
      },
      "conditions_met": 3
    },
    {
      "symbol": "EURGBP",
      "price": 0.85058,
      "signal": "WAIT",
      "direction": "BULL",
      "conditions": {
        "trend": true,
        "channel": true,
        "macd": true,
        "mtf": true,
        "ses": false
      },
      "conditions_met": 4
    }
  ]
}